Metadata-Version: 2.1
Name: algovera-ocean-lib
Version: 1.2.0
Summary: 🐳 Ocean protocol library.
Home-page: https://github.com/oceanprotocol/ocean.py
Author: leucothia
Author-email: devops@oceanprotocol.com
License: Apache Software License 2.0
Keywords: algovera-ocean-lib
Classifier: Development Status :: 2 - Pre-Alpha
Classifier: Intended Audience :: Developers
Classifier: License :: OSI Approved :: Apache Software License
Classifier: Natural Language :: English
Classifier: Programming Language :: Python :: 3.8
License-File: LICENSE
Requires-Dist: ocean-contracts (==1.0.0)
Requires-Dist: coloredlogs
Requires-Dist: pyopenssl
Requires-Dist: PyJWT
Requires-Dist: PyYAML (==5.4.1)
Requires-Dist: requests (>=2.21.0)
Requires-Dist: deprecated
Requires-Dist: pycryptodomex
Requires-Dist: tqdm
Requires-Dist: pytz
Requires-Dist: web3 (==5.28.0)
Requires-Dist: cryptography (==3.3.2)
Requires-Dist: scipy
Requires-Dist: enforce-typing (==1.0.0.post1)
Requires-Dist: json-sempai (==0.4.0)
Requires-Dist: eciespy
Provides-Extra: dev
Requires-Dist: bumpversion ; extra == 'dev'
Requires-Dist: pkginfo ; extra == 'dev'
Requires-Dist: twine ; extra == 'dev'
Requires-Dist: watchdog ; extra == 'dev'
Requires-Dist: flake8 (==3.9.2) ; extra == 'dev'
Requires-Dist: isort (==5.10.1) ; extra == 'dev'
Requires-Dist: black (==22.1.0) ; extra == 'dev'
Requires-Dist: pre-commit ; extra == 'dev'
Requires-Dist: pytest ; extra == 'dev'
Requires-Dist: licenseheaders (==0.8.8) ; extra == 'dev'
Requires-Dist: pytest-env ; extra == 'dev'
Requires-Dist: codacy-coverage ; extra == 'dev'
Requires-Dist: coverage ; extra == 'dev'
Requires-Dist: docker ; extra == 'dev'
Requires-Dist: mccabe ; extra == 'dev'
Requires-Dist: pylint ; extra == 'dev'
Requires-Dist: pytest-watch ; extra == 'dev'
Requires-Dist: Pillow ; extra == 'dev'
Requires-Dist: matplotlib ; extra == 'dev'
Requires-Dist: mkcodes (==0.1.1) ; extra == 'dev'
Provides-Extra: test
Requires-Dist: codacy-coverage ; extra == 'test'
Requires-Dist: coverage ; extra == 'test'
Requires-Dist: docker ; extra == 'test'
Requires-Dist: mccabe ; extra == 'test'
Requires-Dist: pylint ; extra == 'test'
Requires-Dist: pytest ; extra == 'test'
Requires-Dist: pytest-watch ; extra == 'test'
Requires-Dist: Pillow ; extra == 'test'
Requires-Dist: matplotlib ; extra == 'test'
Requires-Dist: mkcodes (==0.1.1) ; extra == 'test'
